napari_spatialdata/__init__.py
napari_spatialdata/__main__.py
napari_spatialdata/_annotationwidgets.py
napari_spatialdata/_interactive.py
napari_spatialdata/_model.py
napari_spatialdata/_reader.py
napari_spatialdata/_scatterwidgets.py
napari_spatialdata/_sdata_widgets.py
napari_spatialdata/_version.py
napari_spatialdata/_view.py
napari_spatialdata/_viewer.py
napari_spatialdata/_widgets.py
napari_spatialdata/napari.yaml
napari_spatialdata/constants/__init__.py
napari_spatialdata/constants/_constants.py
napari_spatialdata/constants/_pkg_constants.py
napari_spatialdata/constants/_utils.py
napari_spatialdata/constants/config.py
napari_spatialdata/resources/exclamation.png
napari_spatialdata/resources/icons8-home-48.png
napari_spatialdata/resources/icons8-pencil-drawing-50.png
napari_spatialdata/resources/icons8-polygon-80.png
napari_spatialdata/resources/icons8-rectangle-48.png
napari_spatialdata/utils/__init__.py
napari_spatialdata/utils/_categoricals_utils.py
napari_spatialdata/utils/_test_utils.py
napari_spatialdata/utils/_utils.py
napari_spatialdata/utils/_viewer_utils.py
napari_spatialdata-0.7.0.dist-info/licenses/LICENSE
napari_spatialdata-0.7.0.dist-info/METADATA
napari_spatialdata-0.7.0.dist-info/WHEEL
napari_spatialdata-0.7.0.dist-info/entry_points.txt
napari_spatialdata-0.7.0.dist-info/top_level.txt
napari_spatialdata-0.7.0.dist-info/RECORD
