Metadata-Version: 2.4
Name: napari-spatialdata
Version: 0.7.0
Summary: Interactive visualization of spatial omics data with napari
Home-page: https://github.com/scverse/napari-spatialdata.git
Author: giovanni palla
Author-email: giov.pll@gmail.com
License: BSD-3-Clause
Project-URL: Bug Tracker, https://github.com/scverse/napari-spatialdata/issues
Project-URL: Documentation, https://spatialdata.scverse.org/projects/napari/en/latest/notebooks/spatialdata.html
Project-URL: Source Code, https://github.com/scverse/napari-spatialdata
Project-URL: User Support, https://github.com/scverse/napari-spatialdata/issues
Classifier: Development Status :: 2 - Pre-Alpha
Classifier: Intended Audience :: Developers
Classifier: Framework :: napari
Classifier: Topic :: Software Development :: Testing
Classifier: Programming Language :: Python
Classifier: Programming Language :: Python :: 3
Classifier: Programming Language :: Python :: 3.11
Classifier: Programming Language :: Python :: 3.12
Classifier: Programming Language :: Python :: 3.13
Classifier: Operating System :: OS Independent
Classifier: License :: OSI Approved :: BSD License
Requires-Python: >=3.11
License-File: LICENSE
Requires-Dist: anndata>=0.12.0
Requires-Dist: click
Requires-Dist: cycler
Requires-Dist: dask>=2025.2.0
Requires-Dist: geopandas
Requires-Dist: loguru
Requires-Dist: matplotlib
Requires-Dist: napari>=0.6.2
Requires-Dist: napari-matplotlib>=3.0.2
Requires-Dist: numba
Requires-Dist: numpy
Requires-Dist: packaging
Requires-Dist: pandas
Requires-Dist: pillow
Requires-Dist: pyqtgraph
Requires-Dist: qtpy
Requires-Dist: scanpy
Requires-Dist: scipy
Requires-Dist: shapely
Requires-Dist: scikit-learn
Requires-Dist: spatialdata>=0.7.0dev1
Requires-Dist: superqt
Requires-Dist: typing_extensions>=4.8.0
Requires-Dist: vispy
Requires-Dist: xarray
Requires-Dist: xarray-datatree
Provides-Extra: bermuda
Requires-Dist: bermuda; extra == "bermuda"
Provides-Extra: test
Requires-Dist: loguru; extra == "test"
Requires-Dist: pytest; extra == "test"
Requires-Dist: pytest-cov; extra == "test"
Requires-Dist: pytest-mock; extra == "test"
Requires-Dist: pytest-qt; extra == "test"
Requires-Dist: pre-commit>=2.9.0; extra == "test"
Provides-Extra: doc
Requires-Dist: sphinx>=4.5; extra == "doc"
Requires-Dist: sphinx-book-theme>=1.0.0; extra == "doc"
Requires-Dist: myst-parser>=2.0.0; extra == "doc"
Requires-Dist: sphinxcontrib-bibtex>=2.5.0; extra == "doc"
Requires-Dist: sphinx-autodoc-typehints>=1.11.0; extra == "doc"
Requires-Dist: sphinx-autobuild; extra == "doc"
Requires-Dist: scanpydoc; extra == "doc"
Requires-Dist: ipykernel; extra == "doc"
Requires-Dist: ipython; extra == "doc"
Requires-Dist: sphinx-copybutton; extra == "doc"
Requires-Dist: sphinx-qt-documentation; extra == "doc"
Requires-Dist: myst-nb>=1.0.0; extra == "doc"
Requires-Dist: squidpy; extra == "doc"
Provides-Extra: readthedocs
Requires-Dist: pydantic>2; extra == "readthedocs"
Provides-Extra: pre
Requires-Dist: spatialdata>=0.7.0dev0; extra == "pre"
Provides-Extra: all
Requires-Dist: napari[pyqt5]; extra == "all"
Dynamic: license-file
